lks_idprovider/__init__.py
lks_idprovider/models/__init__.py
lks_idprovider/models/auth.py
lks_idprovider/models/config/__init__.py
lks_idprovider/models/config/base.py
lks_idprovider/models/config/cache.py
lks_idprovider/models/config/client_credentials.py
lks_idprovider/models/config/jwt.py
lks_idprovider/models/errors/__init__.py
lks_idprovider/models/errors/auth.py
lks_idprovider/models/errors/authentication_required.py
lks_idprovider/models/errors/authorization.py
lks_idprovider/models/errors/base.py
lks_idprovider/models/errors/client_credentials.py
lks_idprovider/models/errors/configuration.py
lks_idprovider/models/errors/network.py
lks_idprovider/models/errors/provider.py
lks_idprovider/models/errors/token.py
lks_idprovider/models/errors/token_expired.py
lks_idprovider/models/errors/token_malformed.py
lks_idprovider/models/errors/token_validation.py
lks_idprovider/models/identity/__init__.py
lks_idprovider/models/identity/client_identity.py
lks_idprovider/models/identity/identity.py
lks_idprovider/models/identity/types.py
lks_idprovider/models/identity/user.py
lks_idprovider/models/role.py
lks_idprovider/models/token/__init__.py
lks_idprovider/models/token/token_info.py
lks_idprovider/models/token/validation_result.py
lks_idprovider/protocols/__init__.py
lks_idprovider/protocols/cache.py
lks_idprovider/protocols/client_credentials.py
lks_idprovider/protocols/provider.py
lks_idprovider/types/__init__.py
lks_idprovider/types/aliases.py
lks_idprovider/types/enums.py
lks_idprovider_api-0.1.6.dist-info/METADATA
lks_idprovider_api-0.1.6.dist-info/WHEEL
lks_idprovider_api-0.1.6.dist-info/RECORD
