Metadata-Version: 2.3
Name: lks-idprovider-api
Version: 0.1.6
Summary: Pure API specification for LKS Identity Provider library with protocols, models, and contracts
License: LKSISL
Author: Raul Medeiros
Author-email: rmedeiros@lksnext.com
Requires-Python: >=3.11
Classifier: License :: Other/Proprietary License
Classifier: Programming Language :: Python :: 3
Classifier: Programming Language :: Python :: 3.11
Classifier: Programming Language :: Python :: 3.12
Classifier: Programming Language :: Python :: 3.13
Requires-Dist: pydantic (>=2.0.0,<3.0.0)
Requires-Dist: pyright (>=1.1.402,<2.0.0)
Requires-Dist: typing-extensions (>=4.0.0)
Project-URL: Documentation, https://github.com/lksnext/lks-idprovider-python#readme
Project-URL: Homepage, https://github.com/lksnext/lks-idprovider-python
Project-URL: Issues, https://github.com/lksnext/lks-idprovider-python/issues
Project-URL: Repository, https://github.com/lksnext/lks-idprovider-python
